README.md
setup.py
NASApi/__init__.py
NASApi/apod.py
NASApi/constants.py
NASApi/earth.py
NASApi/epic.py
NASApi/insight.py
NASApi.egg-info/PKG-INFO
NASApi.egg-info/SOURCES.txt
NASApi.egg-info/dependency_links.txt
NASApi.egg-info/requires.txt
NASApi.egg-info/top_level.txt