Metadata-Version: 2.1
Name: NASApi
Version: 0.0.5
Summary: Simple NASA API wrapper
Home-page: https://github.com/SleepingStar/NASApi
Author: SleepingStar
Author-email: mattisverytoxic@gmail.com
License: UNKNOWN
Keywords: python NASA py
Platform: UNKNOWN
